rocketai/__init__.py
rocketai/rocket.py
RocketAI-0.0.1.dist-info/METADATA
RocketAI-0.0.1.dist-info/WHEEL
RocketAI-0.0.1.dist-info/top_level.txt
RocketAI-0.0.1.dist-info/RECORD
